grscheller/experimental/__init__.py
grscheller/experimental/lazy.py
grscheller/experimental/py.typed
grscheller_experimental-0.5.0.dist-info/LICENSE
grscheller_experimental-0.5.0.dist-info/WHEEL
grscheller_experimental-0.5.0.dist-info/METADATA
grscheller_experimental-0.5.0.dist-info/RECORD
