Metadata-Version: 2.3
Name: grscheller.experimental
Version: 0.5.0
Summary: ### Experimental Modules - OBSOLETED
Keywords: lazy,non-strict
Author-email: "Geoffrey R. Scheller" <geoffrey@scheller.com>
Requires-Python: >=3.12
Classifier: Development Status :: 2 - Pre-Alpha
Classifier: Framework :: Pytest
Classifier: Intended Audience :: Developers
Classifier: License :: OSI Approved :: Apache Software License
Classifier: Operating System :: OS Independent
Classifier: Programming Language :: Python :: 3.12
Classifier: Programming Language :: Python :: 3.13
Classifier: Typing :: Typed
Requires-Dist: grscheller.fp >= 1.1.0, < 1.2
Requires-Dist: pytest >=8.3 ; extra == "test"
Project-URL: Changelog, https://github.com/grscheller/experimental/blob/main/CHANGELOG.md
Project-URL: Documentation, https://grscheller.github.io/grscheller-pypi-namespace-docs/experimental
Project-URL: Source, https://github.com/grscheller/experimental
Provides-Extra: test
